fastapi_vue/__init__.py
fastapi_vue/hostutil.py
fastapi_vue/staticfiles.py
fastapi_vue-0.5.2.dist-info/METADATA
fastapi_vue-0.5.2.dist-info/WHEEL
fastapi_vue-0.5.2.dist-info/RECORD
