Metadata-Version: 2.4
Name: fastapi-vue
Version: 0.5.2
Summary: Serves Vue assets on a FastAPI app. Use fastapi-vue-setup tool to add Vue build to your package.
Project-URL: Homepage, https://git.zi.fi/LeoVasanko/fastapi-vue
Project-URL: Repository, https://github.com/LeoVasanko/fastapi-vue
Requires-Python: >=3.11
Requires-Dist: blake3>=1.0.8
Requires-Dist: fastapi>=0.115.0
Requires-Dist: zstandard>=0.23.0
